odoo/addons/fieldservice_distribution/README.rst
odoo/addons/fieldservice_distribution/__init__.py
odoo/addons/fieldservice_distribution/__manifest__.py
odoo/addons/fieldservice_distribution/i18n/de.po
odoo/addons/fieldservice_distribution/i18n/es.po
odoo/addons/fieldservice_distribution/i18n/es_AR.po
odoo/addons/fieldservice_distribution/i18n/es_CL.po
odoo/addons/fieldservice_distribution/i18n/fieldservice_distribution.pot
odoo/addons/fieldservice_distribution/i18n/pt_BR.po
odoo/addons/fieldservice_distribution/models/__init__.py
odoo/addons/fieldservice_distribution/models/fsm_location.py
odoo/addons/fieldservice_distribution/readme/CONTRIBUTORS.rst
odoo/addons/fieldservice_distribution/readme/CREDITS.rst
odoo/addons/fieldservice_distribution/readme/DESCRIPTION.rst
odoo/addons/fieldservice_distribution/readme/ROADMAP.rst
odoo/addons/fieldservice_distribution/readme/USAGE.rst
odoo/addons/fieldservice_distribution/static/description/icon.png
odoo/addons/fieldservice_distribution/static/description/index.html
odoo/addons/fieldservice_distribution/tests/__init__.py
odoo/addons/fieldservice_distribution/tests/test_fsm_distribution.py
odoo/addons/fieldservice_distribution/views/fsm_location.xml
odoo14_addon_fieldservice_distribution-14.0.1.0.1.dist-info/METADATA
odoo14_addon_fieldservice_distribution-14.0.1.0.1.dist-info/WHEEL
odoo14_addon_fieldservice_distribution-14.0.1.0.1.dist-info/top_level.txt
odoo14_addon_fieldservice_distribution-14.0.1.0.1.dist-info/RECORD
